.gitignore
LICENSE
MANIFEST.in
Pipfile
Pipfile.lock
README.md
setup.cfg
setup.py
tox.ini
setuptools_scm_semver/__init__.py
setuptools_scm_semver/git.py
setuptools_scm_semver/version.py
setuptools_scm_semver.egg-info/PKG-INFO
setuptools_scm_semver.egg-info/SOURCES.txt
setuptools_scm_semver.egg-info/dependency_links.txt
setuptools_scm_semver.egg-info/entry_points.txt
setuptools_scm_semver.egg-info/top_level.txt
setuptools_scm_semver.egg-info/zip-safe
tests/conftest.py
tests/test_git.py